mtcli_conta/__init__.py
mtcli_conta/conta.py
mtcli_conta-0.2.3.dist-info/entry_points.txt
mtcli_conta-0.2.3.dist-info/LICENSE
mtcli_conta-0.2.3.dist-info/METADATA
mtcli_conta-0.2.3.dist-info/WHEEL
mtcli_conta-0.2.3.dist-info/RECORD
