Metadata-Version: 2.3
Name: mtcli-conta
Version: 0.2.3
Summary: Plugin mtcli para exibir dados da conta
Author: Valmir França da Silva
Author-email: vfranca3@gmail.com
Requires-Python: >=3.10,<3.14.0
Classifier: Programming Language :: Python :: 3
Classifier: Programming Language :: Python :: 3.10
Classifier: Programming Language :: Python :: 3.11
Classifier: Programming Language :: Python :: 3.12
Classifier: Programming Language :: Python :: 3.13
Requires-Dist: mtcli (>=1.18.1)
Project-URL: Documentation, https://vfranca.github.io/mtcli-conta
Project-URL: Homepage, https://github.com/vfranca/mtcli-conta
Project-URL: Repository, https://github.com/vfranca/mtcli-conta
Project-URL: issues, https://github.com/vfranca/mtcli-conta/issues
